<MeanCloud_Pumpkins>

  <!-- DOUGH: Removing as this line gives a warning
  <remove xpath="/Ignore_Warnings_In_This_Modelet[@modname='MeanCloud_Pumpkins'][@filename='\Config\blockplaceholders.xml']" />
  -->

  <!-- DOUGH:
  NOTE: Removed and replaced placeholder are identical to vanilla a19.2
  Can likely remove this file unless this is to ensure earlier looaded mods do not overwrite?
  -->
  <remove xpath="/blockplaceholders/placeholder[@name='plantedPumpkin3HarvestRandomHelper']" />

  <append xpath="/blockplaceholders">

    <placeholder name="plantedPumpkin3HarvestRandomHelper">
      <block name="plantedPumpkin3Harvest" prob="0.086" randomrotation="true"/>
      <block name="air" prob="0.1"/>
      <block name="treeSnowyGrassDiagonal" prob="0.431" biome="snow" randomrotation="true"/>
      <block name="treeTallGrassDiagonal" prob="0.431" biome="pine_forest" randomrotation="true"/>
      <block name="treeBrownGrassDiagonal" prob="0.431" biome="desert" randomrotation="true"/>
      <block name="treeBrownGrassDiagonal" prob="0.431" biome="water" randomrotation="true"/>
      <block name="treeBrownGrassDiagonal" prob="0.431" biome="wasteland" randomrotation="true"/>
      <block name="treeBrownGrassDiagonal" prob="0.431" biome="burnt_forest" randomrotation="true"/>
    </placeholder>

  </append>

</MeanCloud_Pumpkins>
